retraites/EtudeImpact.py
retraites/FonctionPension.py
retraites/ModelePensionProbabiliste.py
retraites/SimulateurAnalyse.py
retraites/SimulateurRetraites.py
retraites/__init__.py
retraites/fileProjection.json
retraites-0.1.1.dist-info/LICENSE
retraites-0.1.1.dist-info/METADATA
retraites-0.1.1.dist-info/WHEEL
retraites-0.1.1.dist-info/top_level.txt
retraites-0.1.1.dist-info/RECORD
