Metadata-Version: 2.1
Name: retraites
Version: 0.1.1
Summary: Simulateur financier du système de retraites
Home-page: https://github.com/brunoscherrer/retraites
Author: Bruno Scherrer and Michaël Baudin
Author-email: michael.baudin@gmail.com
Maintainer: Michaël Baudin
Maintainer-email: michael.baudin@gmail.com
License: GPL
Keywords: graphics
Platform: UNKNOWN
Classifier: Development Status :: 5 - Production/Stable
Classifier: Environment :: Console
Classifier: License :: OSI Approved :: GNU General Public License (GPL)
Classifier: Intended Audience :: Science/Research
Classifier: Intended Audience :: Developers
Classifier: Natural Language :: French
Classifier: Programming Language :: Python :: 3
Classifier: Topic :: Software Development
Classifier: Topic :: Scientific/Engineering
Requires-Dist: numpy
Requires-Dist: matplotlib
Requires-Dist: scipy
Requires-Dist: openturns
